{
    "World Champions: 2011": [
        "Karthus",
        "Janna",
        "Corki",
        "JarvanIV",
        "Gragas"
    ],
    "World Champions: 2012": [
        "Nunu",
        "DrMundo",
        "Orianna",
        "Ezreal",
        "Shen"
    ],
    "World Champions: 2013": [
        "Jax",
        "LeeSin",
        "Vayne",
        "Zyra",
        "Zed"
    ],
    "World Champions: 2014": [
        "Singed",
        "Twitch",
        "Talon",
        "Rengar",
        "Thresh"
    ],
    "World Champions: 2015": [
        "Alistar",
        "Ryze",
        "Renekton",
        "Elise",
        "Azir",
        "Kalista"
    ],
    "World Champions: 2016": [
        "Olaf",
        "Syndra",
        "Zac",
        "Jhin",
        "Ekko",
        "Nami"
    ],
    "Victorious": [
        "Sivir",
        "Tryndamere",
        "Morgana",
        "Anivia",
        "Janna",
        "Blitzcrank",
        "Maokai",
        "JarvanIV",
        "Elise",
        "Orianna",
        "Graves",
        "Sejuani",
        "Lucian",
        "Aatrox"
    ],
    "World Championship": [
        "Leblanc",
        "Ryze",
        "Ashe",
        "Renekton",
        "JarvanIV",
        "Riven",
        "Shyvana",
        "KhaZix",
        "Zed",
        "Azir",
        "Thresh",
        "Kalista"
    ],
    "Challenger": [
        "Nidalee",
        "Ahri"
    ],
    "Arcade: Heroes": [
        "MissFortune",
        "Sona",
        "Corki",
        "Caitlyn",
        "Ezreal",
        "Riven",
        "Ahri",
        "Hecarim",
        "Kaisa"
    ],
    "Arcade: Battle Bosses": [
        "Veigar",
        "Blitzcrank",
        "Brand",
        "Malzahar",
        "Ziggs",
        "Yasuo",
        "Belveth",
        "Qiyana"
    ],
    "Blood Moon": [
        "TwistedFate",
        "MasterYi",
        "Sivir",
        "Tryndamere",
        "Zilean",
        "Evelynn",
        "Katarina",
        "Elise",
        "Akali",
        "Kennen",
        "Talon",
        "Shen",
        "Diana",
        "Yasuo",
        "Jhin",
        "Aatrox",
        "Thresh",
        "Kalista",
        "Pyke"
    ],
    "Dragon World": [
        "Olaf",
        "Galio",
        "XinZhao",
        "Kayle",
        "Tristana",
        "Twitch",
        "Trundle",
        "Swain",
        "JarvanIV",
        "Vayne",
        "Heimerdinger",
        "Udyr",
        "Poppy",
        "Pantheon",
        "Mordekaiser",
        "Lulu",
        "Diana",
        "Zyra",
        "Braum"
    ],
    "Omega Squad": [
        "Teemo",
        "Tristana",
        "Twitch",
        "Veigar",
        "Fizz"
    ],
    "Pool Party": [
        "MissFortune",
        "Singed",
        "DrMundo",
        "Gangplank",
        "Taric",
        "Caitlyn",
        "Renekton",
        "JarvanIV",
        "Orianna",
        "LeeSin",
        "Heimerdinger",
        "Leona",
        "Graves",
        "Fiora",
        "Ziggs",
        "Lulu",
        "Draven",
        "Syndra",
        "Zoe",
        "Zac",
        "Taliyah",
        "Braum",
        "RekSai",
        "Sett"
    ],
    "Pentakill": [
        "Olaf",
        "Kayle",
        "Karthus",
        "Sona",
        "Mordekaiser",
        "Yorick"
    ],
    "Program": [
        "Leblanc",
        "Soraka",
        "Blitzcrank",
        "Lissandra",
        "Camille",
        "Nami"
    ],
    "PROJECT": [
        "MasterYi",
        "Warwick",
        "Ashe",
        "Jax",
        "Irelia",
        "Gangplank",
        "Katarina",
        "Renekton",
        "Vayne",
        "Mordekaiser",
        "Akali",
        "Leona",
        "Varus",
        "Sejuani",
        "Fiora",
        "Yasuo",
        "Jhin",
        "Jinx",
        "Senna",
        "Lucian",
        "Zed",
        "Ekko",
        "Vi",
        "Sylas",
        "Pyke",
        "Naafiri"
    ],
    "Super Galaxy": [
        "Annie",
        "Elise",
        "Rumble",
        "Nidalee",
        "Shyvana",
        "Fizz",
        "Gnar",
        "Kindred"
    ],
    "Academy": [
        "Vladimir",
        "Ryze",
        "Ahri",
        "Fiora",
        "Darius",
        "Ekko"
    ],
    "Debonair": [
        "Galio",
        "Leblanc",
        "MasterYi",
        "Brand",
        "Ezreal",
        "Leona",
        "Malzahar",
        "Draven",
        "Jayce",
        "Zed",
        "Vi"
    ],
    "Arclight": [
        "Brand",
        "Vayne",
        "Yorick",
        "Varus",
        "Velkoz"
    ],
    "Battlecast": [
        "Urgot",
        "Singed",
        "Chogath",
        "Caitlyn",
        "Skarner",
        "Nasus",
        "Yorick",
        "KogMaw",
        "Xerath",
        "Viktor",
        "Jayce",
        "Zac",
        "Velkoz",
        "Illaoi"
    ],
    "Culinary Masters": [
        "Olaf",
        "Galio",
        "Sivir",
        "Morgana",
        "Pantheon",
        "Akali",
        "Leona",
        "TahmKench"
    ],
    "Vandal": [
        "Vladimir",
        "Jax",
        "Twitch",
        "Brand",
        "Gragas",
        "Graves"
    ],
    "Winter Sports": [
        "Fiddlesticks",
        "Jax",
        "Twitch",
        "Amumu",
        "Anivia",
        "Kassadin",
        "Corki",
        "Veigar"
    ],
    "Worldbreaker": [
        "Sion",
        "Karma",
        "Trundle",
        "Maokai",
        "Brand",
        "Nasus",
        "Malzahar",
        "Nautilus",
        "Hecarim"
    ],
    "Headhunter": [
        "MasterYi",
        "Caitlyn",
        "Nidalee",
        "Akali",
        "Rengar"
    ],
    "Soccer Cup": [
        "TwistedFate",
        "Alistar",
        "Rammus",
        "Blitzcrank",
        "Katarina",
        "Maokai",
        "LeeSin",
        "Gragas",
        "Ezreal",
        "Akali",
        "Lucian"
    ],
    "Prehistoric Hunters": [
        "Ryze",
        "Sivir",
        "Tryndamere",
        "Chogath",
        "Anivia",
        "Renekton",
        "Udyr",
        "Shyvana",
        "Sejuani",
        "Draven"
    ],
    "Justicar": [
        "Syndra",
        "Aatrox"
    ],
    "Luchador": [
        "DrMundo",
        "Volibear",
        "Gnar",
        "Braum"
    ],
    "Mecha": [
        "Sion",
        "Malphite",
        "Rengar",
        "KhaZix",
        "AurelionSol",
        "Aatrox"
    ],
    "Pulsefire": [
        "TwistedFate",
        "Caitlyn",
        "Pantheon",
        "Ezreal",
        "Riven",
        "Shen",
        "Fiora",
        "Lucian",
        "Ekko",
        "Thresh"
    ],
    "Riot": [
        "Kayle",
        "Tristana",
        "Singed",
        "Blitzcrank",
        "Nasus",
        "Graves"
    ],
    "Rift Quest": [
        "Ryze",
        "Sion",
        "Soraka",
        "Nunu",
        "Twitch",
        "Karthus",
        "DrMundo",
        "Taric",
        "Veigar",
        "Gragas",
        "Mordekaiser",
        "Garen",
        "Talon",
        "Varus",
        "Sejuani",
        "Darius",
        "Jayce",
        "Braum",
        "Bard"
    ],
    "High Noon": [
        "TwistedFate",
        "Urgot",
        "Fiddlesticks",
        "Alistar",
        "Sion",
        "MissFortune",
        "Ashe",
        "Evelynn",
        "Twitch",
        "Irelia",
        "Caitlyn",
        "Katarina",
        "Cassiopeia",
        "Skarner",
        "Gragas",
        "Mordekaiser",
        "Leona",
        "Talon",
        "KogMaw",
        "Varus",
        "Viktor",
        "Hecarim",
        "Darius",
        "Yasuo",
        "Jhin",
        "TahmKench",
        "Senna",
        "Lucian",
        "Samira",
        "Thresh",
        "Rell",
        "Yone"
    ],
    "Hextech": [
        "Annie",
        "Galio",
        "Alistar",
        "Sion",
        "Tristana",
        "Singed",
        "Amumu",
        "Rammus",
        "Anivia",
        "Kassadin",
        "Janna",
        "Swain",
        "Nocturne",
        "Renekton",
        "JarvanIV",
        "Poppy",
        "Malzahar",
        "KogMaw",
        "Sejuani",
        "Ziggs"
    ],
    "Highstakes": [
        "TwistedFate",
        "Shaco",
        "Ezreal",
        "Mordekaiser",
        "Syndra"
    ],
    "Piltover Customs": [
        "Corki",
        "Blitzcrank",
        "Heimerdinger"
    ],
    "Cosmic": [
        "XinZhao",
        "Vladimir",
        "MasterYi",
        "Sion",
        "Nunu",
        "Ashe",
        "Anivia",
        "Kassadin",
        "Skarner",
        "Nidalee",
        "Lux",
        "Varus",
        "Nautilus",
        "Lulu",
        "Hecarim",
        "Belveth",
        "Nami",
        "Illaoi",
        "Rakan",
        "Xayah"
    ],
    "Dark Star": [
        "Chogath",
        "Shaco",
        "Karma",
        "Malphite",
        "JarvanIV",
        "Orianna",
        "Mordekaiser",
        "Lux",
        "Xerath",
        "Varus",
        "KhaZix",
        "Lissandra",
        "Jhin",
        "Thresh"
    ],
    "Marauder": [
        "Olaf",
        "XinZhao",
        "Alistar",
        "Warwick",
        "Ashe",
        "Kled",
        "Kalista"
    ],
    "Snow Day": [
        "Singed",
        "Malzahar",
        "Graves",
        "Ziggs",
        "Syndra",
        "Gnar",
        "Bard"
    ],
    "Winter Wonder": [
        "Annie",
        "MasterYi",
        "Sivir",
        "Soraka",
        "Twitch",
        "DrMundo",
        "Irelia",
        "Karma",
        "Orianna",
        "Poppy",
        "Sejuani",
        "Lulu",
        "Neeko"
    ],
    "Snowdown Showdown": [
        "Leblanc",
        "Teemo",
        "Tristana",
        "Nunu",
        "MissFortune",
        "Zilean",
        "Amumu",
        "Shaco",
        "Sona",
        "Veigar",
        "Katarina",
        "Maokai",
        "Heimerdinger",
        "Nidalee",
        "Gragas",
        "KogMaw",
        "Draven",
        "Braum",
        "Jinx"
    ],
    "Bilgewater: Burning Tides": [
        "TwistedFate",
        "Fiddlesticks",
        "Ryze",
        "Tristana",
        "MissFortune",
        "Twitch",
        "Gangplank",
        "Swain",
        "Malphite",
        "Katarina",
        "Rumble",
        "Garen",
        "Graves",
        "Quinn",
        "Aatrox"
    ],
    "Warden": [
        "Sivir",
        "Jax",
        "Karma",
        "Gragas",
        "Nautilus",
        "Quinn"
    ],
    "Crime City": [
        "MissFortune",
        "Twitch",
        "LeeSin",
        "Gragas",
        "Graves",
        "Braum",
        "Jinx"
    ],
    "Thunder Lord": [
        "Volibear",
        "Ornn"
    ],
    "Lunar Revel: Warring Kingdoms": [
        "XinZhao",
        "Tryndamere",
        "Katarina",
        "JarvanIV",
        "Nidalee",
        "Garen",
        "Talon",
        "Riven",
        "Vi",
        "Azir"
    ],
    "Lunar Revel: Firecracker": [
        "Annie",
        "XinZhao",
        "Teemo",
        "Tristana",
        "Corki",
        "Vayne",
        "KogMaw",
        "Sejuani",
        "Diana",
        "Jinx",
        "Sett"
    ],
    "Lunar Revel": [
        "Warwick",
        "Ashe",
        "Morgana",
        "Sona",
        "Caitlyn",
        "Malphite",
        "MonkeyKing",
        "LeeSin",
        "Cassiopeia",
        "Nasus",
        "Lux",
        "KhaZix",
        "Diana",
        "TahmKench",
        "Qiyana",
        "Thresh",
        "Sylas"
    ],
    "Cottontail": [
        "Teemo",
        "Fizz"
    ],
    "Sugar Rush": [
        "Fiddlesticks",
        "Zilean",
        "Evelynn",
        "Poppy",
        "Ziggs",
        "Lulu",
        "Braum",
        "Ivern"
    ],
    "Elderwood": [
        "Leblanc",
        "Soraka",
        "Karthus",
        "Taric",
        "Veigar",
        "Nocturne",
        "MonkeyKing",
        "Ahri",
        "Hecarim",
        "Gnar",
        "Azir",
        "RekSai",
        "Bard",
        "Rakan",
        "Xayah",
        "Ornn"
    ],
    "Eternum": [
        "Nocturne",
        "Cassiopeia",
        "RekSai"
    ],
    "Order of the Lotus": [
        "Irelia",
        "Karma"
    ],
    "Toy Box": [
        "Alistar",
        "Nunu",
        "Gangplank",
        "Renekton",
        "Orianna",
        "Poppy",
        "KogMaw",
        "Gnar"
    ],
    "Death Blossom": [
        "Elise",
        "KhaZix"
    ],
    "arcticops": [
        "Swain",
        "Caitlyn",
        "Gragas",
        "Kennen",
        "Volibear",
        "Varus"
    ],
    "Heartbreakers": [
        "Annie",
        "Ashe",
        "Sona",
        "Orianna",
        "Vayne",
        "Varus",
        "Fiora",
        "Quinn",
        "Jinx",
        "Lucian",
        "Vi",
        "Yuumi",
        "Rakan",
        "Xayah"
    ],
    "Steel Valkyries": [
        "Kayle",
        "MissFortune",
        "Morgana",
        "Janna",
        "Nasus",
        "Kaisa",
        "Camille",
        "Lucian",
        "Renata"
    ],
    "Guardian of the Sands": [
        "Fiddlesticks",
        "Ryze",
        "Rammus",
        "Janna",
        "Katarina",
        "Skarner",
        "Xerath",
        "Rengar",
        "KhaZix",
        "Ekko",
        "Pyke"
    ],
    "Pharaoh": [
        "Amumu",
        "Nasus",
        "Nidalee"
    ],
    "Woad": [
        "Kayle",
        "Ashe",
        "Morgana",
        "Darius",
        "Quinn"
    ],
    "Lancer": [
        "Blitzcrank",
        "MonkeyKing",
        "Hecarim"
    ],
    "Road Warrior": [
        "Warwick",
        "MissFortune",
        "Veigar",
        "Trundle",
        "Brand",
        "Rumble",
        "Heimerdinger",
        "Pantheon"
    ],
    "Storybook": [
        "Annie",
        "Vladimir",
        "Warwick",
        "Shaco",
        "KogMaw"
    ],
    "Fables": [
        "TwistedFate",
        "Nunu",
        "Morgana",
        "Chogath",
        "Sona",
        "Veigar",
        "Cassiopeia",
        "Pantheon",
        "Leona",
        "Malzahar",
        "Fiora",
        "Diana",
        "Nami"
    ],
    "Odyssey": [
        "TwistedFate",
        "Sivir",
        "Sona",
        "Karma",
        "Malphite",
        "Ziggs",
        "KhaZix",
        "Kayn",
        "Yasuo",
        "Jinx",
        "Zed",
        "Aatrox"
    ],
    "Bilgewater: Curse of the Drowned": [
        "Vladimir",
        "Diana",
        "Kayn"
    ],
    "World Champions: 2017": [
        "JarvanIV",
        "Ezreal",
        "Gnar",
        "Taliyah",
        "Rakan",
        "Xayah"
    ],
    "Dreadnova": [
        "Gangplank",
        "Darius"
    ],
    "Battle of the God-Kings": [
        "Garen",
        "Darius"
    ],
    "Kaiju": [
        "Urgot"
    ],
    "Omen of the Dark": [
        "Fiddlesticks",
        "Kayle",
        "Warwick",
        "Singed",
        "DrMundo",
        "Nocturne",
        "Yorick",
        "Lissandra"
    ],
    "Immortal Journey": [
        "Kayle",
        "MasterYi",
        "Soraka",
        "Jax",
        "Morgana",
        "Sona",
        "Irelia",
        "Janna",
        "LeeSin",
        "Talon",
        "Riven",
        "Shyvana",
        "Fiora",
        "Zeri",
        "Zed",
        "Nami"
    ],
    "Traditional": [
        "Karma",
        "Trundle",
        "LeeSin",
        "Sejuani"
    ],
    "Collector's Edition": [
        "Kayle",
        "Alistar",
        "Ryze"
    ],
    "PAX": [
        "TwistedFate",
        "Sivir",
        "Jax"
    ],
    "Steel Legion": [
        "Garen",
        "Lux"
    ],
    "Infernal": [
        "Galio",
        "Alistar",
        "Warwick",
        "Karthus",
        "Amumu",
        "Rammus",
        "Malphite",
        "Maokai",
        "Renekton",
        "MonkeyKing",
        "Nasus",
        "Mordekaiser",
        "Akali",
        "Kennen",
        "Shen",
        "Xerath",
        "Ahri",
        "Varus",
        "Diana",
        "AurelionSol",
        "Zyra",
        "Velkoz",
        "Kindred"
    ],
    "Death Sworn": [
        "Soraka",
        "Evelynn",
        "Katarina",
        "MonkeyKing",
        "Viktor",
        "Sejuani",
        "Draven",
        "Hecarim",
        "Zed",
        "Azir"
    ],
    "Trick-or-Treat": [
        "Annie",
        "TwistedFate",
        "Urgot",
        "Leblanc",
        "Vladimir",
        "Fiddlesticks",
        "Tryndamere",
        "Karthus",
        "Amumu",
        "DrMundo",
        "Kassadin",
        "Gangplank",
        "Blitzcrank",
        "Katarina",
        "Nocturne",
        "Maokai",
        "Vayne",
        "Lulu",
        "Hecarim",
        "Zyra",
        "Kled",
        "Ekko"
    ],
    "Zombies VS Slayers": [
        "Ryze",
        "Nunu",
        "Brand",
        "Pantheon",
        "Jinx"
    ],
    "Praetorian": [
        "Fiddlesticks",
        "Graves"
    ],
    "K/DA": [
        "Evelynn",
        "Akali",
        "Ahri",
        "Kaisa",
        "Seraphine"
    ],
    "Coven": [
        "Leblanc",
        "Warwick",
        "Ashe",
        "Morgana",
        "Evelynn",
        "Malphite",
        "Nocturne",
        "Elise",
        "Cassiopeia",
        "Mordekaiser",
        "Akali",
        "Ahri",
        "Volibear",
        "Lissandra",
        "Syndra",
        "Zyra",
        "Camille",
        "Nami",
        "Ivern",
        "Nilah"
    ],
    "Eclipse": [
        "Kayle",
        "Sivir",
        "Leona",
        "Sejuani",
        "Senna",
        "Aatrox"
    ],
    "Astronauts": [
        "Teemo",
        "Singed",
        "Rammus",
        "Corki",
        "Veigar",
        "Maokai",
        "Poppy",
        "Kennen",
        "Xerath",
        "Fizz",
        "Nautilus",
        "Gnar",
        "Ivern",
        "Bard"
    ],
    "Arcanists": [
        "Shaco",
        "KogMaw",
        "Lux",
        "Ziggs",
        "Zoe"
    ],
    "Papercraft": [
        "Nunu",
        "Anivia"
    ],
    "Albion": [
        "Kayle",
        "Ashe",
        "Morgana",
        "Ezreal"
    ],
    "Cats Versus Dogs": [
        "Corki",
        "Maokai",
        "Nidalee",
        "Yorick",
        "Fizz",
        "Rengar",
        "Kindred",
        "Kled",
        "Yuumi"
    ],
    "Wonders of the World": [
        "XinZhao",
        "Ryze",
        "Teemo",
        "Tryndamere",
        "Karthus",
        "Anivia",
        "Shaco",
        "Gangplank",
        "Malphite",
        "Renekton",
        "LeeSin",
        "Gragas",
        "Pantheon",
        "Malzahar",
        "Ahri",
        "Sejuani"
    ],
    "Day Job": [
        "Annie",
        "Olaf",
        "Leblanc",
        "Alistar",
        "Sion",
        "Tristana",
        "Jax",
        "Zilean",
        "Chogath",
        "Amumu",
        "DrMundo",
        "Irelia",
        "Janna",
        "Gangplank",
        "Trundle",
        "Blitzcrank",
        "Heimerdinger",
        "Nidalee",
        "Udyr",
        "Gragas",
        "Riven",
        "KogMaw",
        "Fizz",
        "Draven"
    ],
    "Definitely Not": [
        "Urgot",
        "Tristana",
        "Veigar",
        "Blitzcrank",
        "Udyr",
        "Malzahar",
        "Draven",
        "Velkoz"
    ],
    "High Society": [
        "TwistedFate",
        "Vladimir",
        "Soraka",
        "Evelynn",
        "Chogath",
        "Vayne",
        "Nasus",
        "Gnar"
    ],
    "Dunkmaster": [
        "Darius",
        "Ivern"
    ],
    "Commando": [
        "Galio",
        "XinZhao",
        "Tristana",
        "Gangplank",
        "JarvanIV",
        "Garen",
        "Lux"
    ],
    "Invaders": [
        "Corki",
        "Heimerdinger"
    ],
    "Mad Scientists": [
        "Zilean",
        "Singed",
        "Amumu",
        "Ziggs"
    ],
    "World Champions: 2018": [
        "Leblanc",
        "Irelia",
        "Fiora",
        "Kaisa",
        "Camille",
        "Rakan"
    ],
    "Forgotten Depths": [
        "Kassadin",
        "Malphite",
        "KogMaw",
        "Fizz",
        "Nautilus",
        "Syndra",
        "Nami",
        "Thresh"
    ],
    "Conqueror": [
        "Alistar",
        "Jax",
        "Karma",
        "Varus",
        "Nautilus"
    ],
    "Goth": [
        "Annie",
        "Amumu",
        "Orianna"
    ],
    "Silver Age": [
        "Teemo",
        "Tristana",
        "Warwick",
        "Tryndamere",
        "Singed",
        "DrMundo",
        "Irelia",
        "Veigar",
        "Nocturne",
        "Brand",
        "Kennen",
        "Darius",
        "Quinn"
    ],
    "Glacial": [
        "Olaf",
        "Malphite",
        "Nocturne",
        "Shen"
    ],
    "Battle Academia": [
        "Caitlyn",
        "Katarina",
        "MonkeyKing",
        "Ezreal",
        "Garen",
        "Leona",
        "Lux",
        "Graves",
        "Jayce",
        "Yuumi",
        "Yone"
    ],
    "Medieval": [
        "Ashe",
        "Tryndamere",
        "Twitch",
        "Amumu",
        "Veigar",
        "Poppy",
        "Lux",
        "Kled"
    ],
    "Rift Hospital": [
        "Akali",
        "Kennen",
        "Shen"
    ],
    "Demonic": [
        "Galio",
        "Teemo",
        "Tristana",
        "Fizz",
        "Vi"
    ],
    "Demacia Vice": [
        "Taric",
        "Garen",
        "Lucian",
        "Vi"
    ],
    "Heavy Metal": [
        "Nunu",
        "Rammus",
        "Pantheon",
        "Viktor",
        "Jayce"
    ],
    "True Damage": [
        "Akali",
        "Yasuo",
        "Senna",
        "Ekko",
        "Qiyana"
    ],
    "Cops and Robbers": [
        "XinZhao",
        "MissFortune",
        "Evelynn",
        "Twitch",
        "Trundle",
        "Caitlyn",
        "Volibear",
        "Vi"
    ],
    "Crimson Elite": [
        "Talon",
        "Riven"
    ],
    "Dreadknights": [
        "Nasus",
        "Garen"
    ],
    "Dawnbringer": [],
    "Nightbringer": [],
    "Bloodstone": [
        "Vladimir",
        "Ryze",
        "Taric",
        "Renekton",
        "Fiora",
        "Hecarim",
        "Lissandra"
    ],
    "Mecha Kingdoms": [
        "Jax",
        "Garen",
        "Leona",
        "Draven",
        "Sett"
    ],
    "Freljord": [
        "Warwick",
        "Ashe",
        "Rammus",
        "Janna",
        "Ezreal",
        "Taliyah",
        "Sylas"
    ],
    "Blackfrost": [
        "Alistar",
        "Sion",
        "Anivia",
        "Renekton",
        "Shyvana",
        "Velkoz",
        "RekSai"
    ],
    "World Champions: 2019": [
        "Gangplank",
        "Malphite",
        "LeeSin",
        "Vayne",
        "Thresh"
    ],
    "PsyOps": [
        "MasterYi",
        "Sona",
        "Ezreal",
        "Shen",
        "Vi"
    ],
    "Black Rose Group": [
        "Kayle",
        "Viktor",
        "Zed",
        "Samira",
        "Pyke"
    ],
    "Dragonmancers": [
        "Ashe",
        "Kassadin",
        "Karma",
        "Brand",
        "LeeSin",
        "Vayne",
        "Volibear",
        "Fiora",
        "AurelionSol",
        "Kaisa",
        "Yasuo",
        "Thresh",
        "Rakan",
        "Sett"
    ],
    "Galactic": [
        "Renekton",
        "Nasus",
        "Azir"
    ],
    "Battle Queens": [
        "Janna",
        "Katarina",
        "Diana",
        "Qiyana",
        "Rell"
    ],
    "Ruined": [
        "MissFortune",
        "Gangplank",
        "Karma",
        "Pantheon",
        "Shyvana",
        "Draven",
        "Yasuo",
        "Thresh"
    ],
    "Shan Hai Scrolls": [
        "Chogath",
        "KogMaw",
        "Nautilus",
        "Jhin",
        "TahmKench",
        "Bard",
        "Neeko",
        "Lillia"
    ],
    "Crystal Rose": [
        "Janna",
        "Swain",
        "Zyra",
        "Akshan"
    ],
    "Withered Rose": [
        "Elise",
        "Talon",
        "Syndra",
        "Zeri"
    ],
    "Lunar Beast": [
        "Annie",
        "Alistar",
        "JarvanIV",
        "Fiora",
        "Darius",
        "Viego",
        "Aphelios"
    ],
    "Bees!": [
        "Teemo",
        "Nunu",
        "Singed",
        "Veigar",
        "Blitzcrank",
        "Orianna",
        "Heimerdinger",
        "Malzahar",
        "KogMaw",
        "Ziggs",
        "Velkoz",
        "Yuumi"
    ],
    "Space Groove": [
        "TwistedFate",
        "Teemo",
        "Nunu",
        "Taric",
        "Blitzcrank",
        "Rumble",
        "Nasus",
        "Gragas",
        "Lux",
        "Lulu",
        "Lissandra",
        "Nami",
        "Samira",
        "Ornn",
        "Gwen"
    ],
    "World Champions: 2020": [
        "TwistedFate",
        "Nidalee",
        "Kennen",
        "Leona",
        "Jhin"
    ],
    "Arcana": [
        "Ryze",
        "Xerath",
        "Ahri",
        "Hecarim",
        "Camille",
        "TahmKench",
        "Lucian",
        "Rakan",
        "Xayah"
    ],
    "Sentinels of Light": [
        "Olaf",
        "Irelia",
        "Vayne",
        "Riven",
        "Graves",
        "Rengar",
        "Diana",
        "Pyke"
    ],
    "Cyber Pop": [
        "Zoe",
        "Akshan"
    ],
    "Crime City Nightmare": [
        "TwistedFate",
        "Shaco",
        "Akali",
        "Darius",
        "Zyra"
    ],
    "Phoenixmancers": [
        "Anivia",
        "Seraphine",
        "Xayah"
    ],
    "Pentakill III: The Lost Chapter": [
        "Olaf",
        "Kayle",
        "Karthus",
        "Sona",
        "Mordekaiser",
        "Yorick",
        "Viego"
    ],
    "Arcane": [
        "Caitlyn",
        "Jayce",
        "Jinx",
        "Ekko",
        "Vi"
    ],
    "Cafe Cuties": [
        "Annie",
        "Vladimir",
        "Sivir",
        "Soraka",
        "Rumble",
        "Poppy",
        "Lulu",
        "Jinx",
        "Bard",
        "Gwen"
    ],
    "Porcelain": [
        "MissFortune",
        "Morgana",
        "Amumu",
        "Irelia",
        "Ezreal",
        "Lux",
        "Graves",
        "Darius",
        "Lissandra",
        "AurelionSol",
        "Kindred"
    ],
    "Shockblade": [
        "Kassadin",
        "Shen",
        "Zed",
        "Qiyana"
    ],
    "Anima Squad": [
        "MissFortune",
        "Vayne",
        "Riven",
        "Jinx",
        "Sylas"
    ],
    "Ashen Knights": [
        "Pantheon",
        "Mordekaiser",
        "Shen",
        "Sylas",
        "Pyke"
    ],
    "World Champions: 2021": [
        "Graves",
        "Zoe",
        "Viego",
        "Yuumi",
        "Aphelios"
    ],
    "Ocean Song": [
        "Ashe",
        "Nidalee",
        "Seraphine",
        "Zeri",
        "Yone"
    ],
    "Snow Moon": [
        "Morgana",
        "Caitlyn",
        "Ahri",
        "Varus",
        "Kayn",
        "Illaoi"
    ],
    "Monster Tamers": [
        "Veigar",
        "KogMaw",
        "Lulu"
    ],
    "Spirit Guard": [
        "Udyr"
    ],
    "Ruination": [
        "Viego"
    ],
    "Zenith Games": [
        "Blitzcrank",
        "LeeSin",
        "Jayce"
    ],
    "Elementalist": [
        "Lux"
    ],
    "Legacy": [
        "Annie",
        "Olaf",
        "Galio",
        "TwistedFate",
        "XinZhao",
        "Leblanc",
        "Kayle",
        "MasterYi",
        "Alistar",
        "Sion",
        "Sivir",
        "Teemo",
        "MissFortune",
        "Ashe",
        "Tryndamere",
        "Jax",
        "Evelynn",
        "Karthus",
        "Chogath",
        "Rammus",
        "Anivia",
        "Shaco",
        "DrMundo",
        "Kassadin",
        "Irelia",
        "Janna",
        "Gangplank",
        "Corki",
        "Karma",
        "Caitlyn",
        "Blitzcrank",
        "Malphite",
        "Katarina",
        "Maokai",
        "JarvanIV",
        "Orianna",
        "MonkeyKing",
        "Rumble",
        "Skarner",
        "Nidalee",
        "Poppy",
        "Gragas",
        "Ezreal",
        "Akali",
        "Kennen",
        "Garen",
        "Leona",
        "Malzahar",
        "Talon",
        "KogMaw",
        "Shen",
        "Lux",
        "Xerath",
        "Shyvana",
        "Ahri",
        "Graves",
        "Fizz",
        "Rengar",
        "Varus",
        "Nautilus",
        "Ziggs",
        "Draven",
        "Jayce",
        "Zac",
        "Lucian",
        "Nami"
    ],
    "Urf the Manatee": [
        "Warwick",
        "Corki",
        "TahmKench",
        "Nami"
    ],
    "Surprise Party": [
        "Annie",
        "Fiddlesticks",
        "Amumu"
    ],
    "Fright Night": [
        "Annie",
        "Urgot",
        "Trundle",
        "Nautilus",
        "Draven",
        "Renata"
    ],
    "Spirit Blossom": [
        "MasterYi",
        "Soraka",
        "Teemo",
        "Tristana",
        "Evelynn",
        "Vayne",
        "Cassiopeia",
        "Yorick",
        "Riven",
        "Ahri",
        "Darius",
        "Syndra",
        "Yasuo",
        "Kindred",
        "Thresh",
        "Aphelios",
        "Yone",
        "Sett",
        "Lillia"
    ],
    "Bewitching": [
        "Leblanc",
        "Tristana",
        "MissFortune",
        "Morgana",
        "Anivia",
        "Janna",
        "Elise",
        "Cassiopeia",
        "Nidalee",
        "Poppy",
        "Fiora",
        "Syndra",
        "Senna",
        "Nami",
        "Yuumi",
        "Neeko"
    ],
    "DJ": [
        "Sona"
    ],
    "Popstar": [
        "Ahri"
    ],
    "Three Honors": [
        "Malzahar",
        "Akshan"
    ],
    "Bilgewater: Mercs": [
        "Katarina"
    ],
    "Chronicle": [
        "XinZhao",
        "Alistar",
        "Zilean"
    ],
    "Curse of the Void": [
        "Kassadin",
        "Nocturne",
        "Fizz",
        "Illaoi"
    ],
    "Otherroads": [
        "Kayle",
        "Soraka",
        "Tryndamere",
        "Swain",
        "Renekton",
        "LeeSin",
        "Poppy",
        "Riven",
        "Volibear",
        "Viktor",
        "Yasuo"
    ],
    "Beta": [
        "Rammus"
    ],
    "Soulstealer": [
        "Vladimir",
        "Vayne"
    ],
    "Triumphant": [
        "Ryze"
    ],
    "True Warrior": [],
    "Empyrean": [
        "Jax",
        "Lux",
        "Zac",
        "Jhin",
        "Zed",
        "Pyke",
        "Vex",
        "KSante"
    ],
    "Winterblessed": [
        "Annie",
        "Warwick",
        "Zilean",
        "Shaco",
        "Swain",
        "Hecarim",
        "Diana",
        "Zoe",
        "Camille",
        "Senna",
        "Lucian",
        "Thresh",
        "Sylas",
        "Hwei"
    ],
    "Mythmaker": [
        "Galio",
        "Sivir",
        "Irelia",
        "Garen",
        "Zyra"
    ],
    "Heartthrobs and Heartaches": [
        "Amumu",
        "Caitlyn",
        "Vi"
    ],
    "Broken Covenant": [
        "Vladimir",
        "MissFortune",
        "Chogath",
        "Nocturne",
        "Riven",
        "Rakan",
        "Xayah"
    ],
    "Faerie Court": [
        "Karma",
        "Katarina",
        "Ezreal",
        "Fiora",
        "Seraphine",
        "Kalista",
        "Milio"
    ],
    "Inkshadow": [
        "MasterYi",
        "Udyr",
        "Volibear",
        "AurelionSol",
        "Kaisa",
        "Yasuo",
        "Yone"
    ],
    "Nightbringer and Dawnbringer": [
        "Vladimir",
        "Soraka",
        "Tryndamere",
        "Morgana",
        "Karma",
        "Renekton",
        "JarvanIV",
        "LeeSin",
        "Vayne",
        "Nasus",
        "Nidalee",
        "Riven",
        "Kayn",
        "Yasuo",
        "Aphelios",
        "Vex",
        "Yone",
        "Lillia"
    ],
    "World Champions: 2022": [
        "Ashe",
        "Caitlyn",
        "Maokai",
        "Akali",
        "Kindred",
        "Aatrox"
    ],
    "Crystalis Motus": [
        "Ashe",
        "Leona",
        "Taliyah"
    ],
    "Soul Fighter": [
        "Evelynn",
        "Shaco",
        "Lux",
        "Jhin",
        "Viego",
        "Samira",
        "Pyke",
        "Sett",
        "Gwen",
        "Naafiri"
    ],
    "Street Demons": [
        "DrMundo",
        "Brand",
        "Rengar",
        "Zyra",
        "Briar",
        "Neeko"
    ],
    "La Ilusión": [
        "Nidalee",
        "Ziggs",
        "Draven",
        "Gnar",
        "Qiyana",
        "Renata"
    ],
    "HEARTSTEEL": [
        "Ezreal",
        "Kayn",
        "Aphelios",
        "Yone",
        "Sett",
        "KSante"
    ],
    "Primal Ambush": [
        "Sivir",
        "Talon",
        "Riven",
        "Vi"
    ],
    "Heavenscale": [
        "MasterYi",
        "Janna",
        "LeeSin",
        "Ezreal",
        "Diana",
        "Kaisa",
        "Smolder"
    ],
    "Crystalis Indomitus": [
        "KhaZix"
    ],
    "Star Guardian": [
        "Janna",
        "Poppy",
        "Lux",
        "Lulu",
        "Jinx",
        "Soraka",
        "MissFortune",
        "Ezreal",
        "Ahri",
        "Syndra",
        "Zoe",
        "Rakan",
        "Xayah",
        "Neeko",
        "Fiddlesticks",
        "Morgana",
        "Sona",
        "Orianna",
        "Akali",
        "Quinn",
        "Syndra",
        "Kaisa",
        "Seraphine",
        "Taliyah",
        "Senna",
        "Ekko",
        "Rakan",
        "Xayah",
        "Rell",
        "Nilah"
    ]
}